epistoch/__init__.py
epistoch/experiments.py
epistoch/seird_ph.py
epistoch/sir_g.py
epistoch/sir_phg.py
epistoch/experimental/__init__.py
epistoch/experimental/sir_gen_experimental.py
epistoch/utils/__init__.py
epistoch/utils/plotting.py
epistoch/utils/stats.py
epistoch/utils/utils.py
pyphase/__init__.py
pyphase/phase.py
epistoch-0.1.13.dist-info/AUTHORS.rst
epistoch-0.1.13.dist-info/LICENSE
epistoch-0.1.13.dist-info/METADATA
epistoch-0.1.13.dist-info/WHEEL
epistoch-0.1.13.dist-info/top_level.txt
epistoch-0.1.13.dist-info/RECORD
