Metadata-Version: 2.1
Name: epistoch
Version: 0.1.13
Summary: Epidemics Models with Random Infectious Period
Home-page: https://github.com/griano/epistoch
Author: Germán Riaño
Author-email: griano@germanriano.com
License: MIT license
Keywords: epistoch
Platform: UNKNOWN
Classifier: Development Status :: 2 - Pre-Alpha
Classifier: Intended Audience :: Developers
Classifier: License :: OSI Approved :: MIT License
Classifier: Natural Language :: English
Classifier: Programming Language :: Python :: 3
Classifier: Programming Language :: Python :: 3.6
Classifier: Programming Language :: Python :: 3.7
Classifier: Programming Language :: Python :: 3.8
Requires-Python: >=3.6
Requires-Dist: numpy (>=1.18)
Requires-Dist: matplotlib (>=3.2)
Requires-Dist: scipy (>=1.4)
Requires-Dist: pandas (>=1.0.3)
Requires-Dist: tqdm (>=4.46.0)
